ylogging_v2/__init__.py
ylogging_v2/lib.py
ylogging_v2-0.1.0.dist-info/licenses/LICENSE
ylogging_v2-0.1.0.dist-info/METADATA
ylogging_v2-0.1.0.dist-info/WHEEL
ylogging_v2-0.1.0.dist-info/top_level.txt
ylogging_v2-0.1.0.dist-info/RECORD
