Metadata-Version: 2.4
Name: ylogging-v2
Version: 0.1.0
Summary: A Python logging package
Author-email: Yacine Touati <yactouat@yactouat.com>
License: MIT
Project-URL: Homepage, https://github.com/yactouat/ylogging_v2
Project-URL: Repository, https://github.com/yactouat/ylogging_v2
Classifier: Development Status :: 3 - Alpha
Classifier: Intended Audience :: Developers
Classifier: License :: OSI Approved :: MIT License
Classifier: Programming Language :: Python :: 3
Classifier: Programming Language :: Python :: 3.8
Classifier: Programming Language :: Python :: 3.9
Classifier: Programming Language :: Python :: 3.10
Classifier: Programming Language :: Python :: 3.11
Classifier: Programming Language :: Python :: 3.12
Requires-Python: >=3.8
License-File: LICENSE
Requires-Dist: google-auth
Requires-Dist: google-cloud-error-reporting
Requires-Dist: google-cloud-logging
Requires-Dist: pydantic
Requires-Dist: pytz
Dynamic: license-file
